<item>
  <title>CSVEditor</title>
  <version>2.0.1.0</version>
  <installUrl>https://tnkbang.github.io/CSVEditor/data/CSVEditor%20Setup.exe</installUrl>
  <portableUrl>https://tnkbang.github.io/CSVEditor/data/CSVEditor-portable.zip</portableUrl>
  <changelog>Các thay đổi sau:
  - Thêm giấy phép cho ứng dụng. Hiện sử dụng giấy phép CC BY-NC 4.0
  - Tối ưu xử lý tìm giá trị và đánh dấu ô.
  Xem chi tiết tại: https://tnkbang.github.io/CSVEditor/changelog.html</changelog>
  <mandatory>false</mandatory>
  <minVersion>2.0.1.0</minVersion>
</item>
